sdbus/__init__.py
sdbus/__main__.py
sdbus/autodoc.py
sdbus/dbus_common_elements.py
sdbus/dbus_common_funcs.py
sdbus/dbus_exceptions.py
sdbus/dbus_proxy_async_interface_base.py
sdbus/dbus_proxy_async_interfaces.py
sdbus/dbus_proxy_async_method.py
sdbus/dbus_proxy_async_object_manager.py
sdbus/dbus_proxy_async_property.py
sdbus/dbus_proxy_async_signal.py
sdbus/dbus_proxy_sync_interface_base.py
sdbus/dbus_proxy_sync_interfaces.py
sdbus/dbus_proxy_sync_method.py
sdbus/dbus_proxy_sync_property.py
sdbus/default_bus.py
sdbus/exceptions.py
sdbus/interface_generator.py
sdbus/py.typed
sdbus/sd_bus_internals.abi3.so
sdbus/sd_bus_internals.h
sdbus/sd_bus_internals.py
sdbus/unittest.py
sdbus/utils/__init__.py
sdbus/utils/inspect.py
sdbus/utils/parse.py
sdbus_async/dbus_daemon/__init__.py
sdbus_async/dbus_daemon/py.typed
sdbus_block/dbus_daemon/__init__.py
sdbus_block/dbus_daemon/py.typed
sdbus-0.14.2.dist-info/COPYING
sdbus-0.14.2.dist-info/COPYING.LESSER
sdbus-0.14.2.dist-info/METADATA
sdbus-0.14.2.dist-info/WHEEL
sdbus-0.14.2.dist-info/top_level.txt
sdbus-0.14.2.dist-info/RECORD
