Metadata-Version: 2.1
Name: sdbus
Version: 0.14.2
Summary: Modern Python D-Bus library. Based on sd-bus from libsystemd.
Home-page: https://github.com/python-sdbus/python-sdbus
Author: igo95862
Author-email: igo95862@yandex.ru
License: LGPL-2.1-or-later
Project-URL: Documentation, https://python-sdbus.readthedocs.io/en/latest/
Project-URL: Source, https://github.com/python-sdbus/python-sdbus/
Project-URL: Tracker, https://github.com/python-sdbus/python-sdbus/issues/
Keywords: dbus ipc linux freedesktop
Platform: UNKNOWN
Classifier: Development Status :: 4 - Beta
Classifier: Intended Audience :: Developers
Classifier: License :: OSI Approved :: GNU Lesser General Public License v2 or later (LGPLv2+)
Classifier: Operating System :: POSIX :: Linux
Classifier: Programming Language :: Python :: 3 :: Only
Classifier: Topic :: Software Development :: Libraries :: Python Modules
Requires-Python: >=3.9
License-File: COPYING
License-File: COPYING.LESSER
